<?xml version="1.0" encoding="UTF-8"?>
<BasicAsset xmlns:md="http://www.movielabs.com/schema/md/v2.3/md" xmlns:ns3="http://www.w3.org/2000/09/xmldsig#" xmlns="http://www.decellc.org/schema/2015/03/coordinator"><BasicData ContentID="urn:dece:cid:eidr-s:1F15-17D4-5AA1-037A-C49F-5"><md:UpdateNum>23536751</md:UpdateNum><md:LocalizedInfo default="true" language="en"><md:TitleDisplay19>To Wong Foo Thanks…</md:TitleDisplay19><md:TitleDisplay60>To Wong Foo, Thanks for Everything! Julie Newmar</md:TitleDisplay60><md:TitleSort>To Wong Foo, Thanks for Everything! Julie Newmar</md:TitleSort><md:ArtReference resolution="112x160">https://g.prod.uvvu.com/artwork/04689ed325de29eae05314345a0a9725</md:ArtReference><md:ArtReference resolution="117x176">https://g.prod.uvvu.com/artwork/04689ed325e029eae05314345a0a9725</md:ArtReference><md:ArtReference resolution="192x288">https://g.prod.uvvu.com/artwork/04689ed325e429eae05314345a0a9725</md:ArtReference><md:ArtReference resolution="224x320">https://g.prod.uvvu.com/artwork/04689ed325e329eae05314345a0a9725</md:ArtReference><md:ArtReference resolution="800x1200">https://g.prod.uvvu.com/artwork/04689ed325e229eae05314345a0a9725</md:ArtReference><md:ArtReference resolution="840x1200">https://g.prod.uvvu.com/artwork/04689ed325e129eae05314345a0a9725</md:ArtReference><md:ArtReference resolution="96x144">https://g.prod.uvvu.com/artwork/04689ed325df29eae05314345a0a9725</md:ArtReference><md:Summary190>Patrick Swayze, John Leguizamo and Wesley Snipes star in this adventure about three “girls” who set out to fix the broken hearts, broken dreams and broken nails of some small-town residents.</md:Summary190><md:Summary400>Patrick Swayze, John Leguizamo and Wesley Snipes star in this adventure about three “girls” who set out to fix the broken hearts, broken dreams and broken nails of some small-town residents.</md:Summary400><md:Summary4000>Patrick Swayze, John Leguizamo and Wesley Snipes star in this hilarious adventure about three transvestites on the cross-country road trip of a lifetime. On their way to Hollywood for a drag queen beauty pageant, Vida (Swayze), Chi Chi (Leguizamo) and Noxeema (Snipes) get stranded in the tiny Midwestern town of Snydersville. Determined to make the best of a bad situation, the “girls” set out to repair the broken hearts, broken dreams and broken nails of the small-town residents during one wildly outrageous weekend.</md:Summary4000><md:Genre>Comedy</md:Genre><md:OriginalTitle>To Wong Foo, Thanks for Everything! Julie Newmar</md:OriginalTitle><md:CopyrightLine>© 1995 Universal Studios. All Rights Reserved.</md:CopyrightLine><md:PeopleLocal><md:Job><md:JobFunction>Actor</md:JobFunction><md:BillingBlockOrder>10</md:BillingBlockOrder><md:Character>Rachel Tensions</md:Character></md:Job><md:Name><md:DisplayName>RuPaul Charles</md:DisplayName><md:SortName>Charles, RuPaul</md:SortName><md:FirstGivenName>RuPaul</md:FirstGivenName><md:FamilyName>Charles</md:FamilyName></md:Name></md:PeopleLocal><md:PeopleLocal><md:Job><md:JobFunction>Actor</md:JobFunction><md:BillingBlockOrder>2</md:BillingBlockOrder><md:Character>Noxeema</md:Character></md:Job><md:Name><md:DisplayName>Wesley Snipes</md:DisplayName><md:SortName>Snipes, Wesley</md:SortName><md:FirstGivenName>Wesley</md:FirstGivenName><md:FamilyName>Snipes</md:FamilyName></md:Name></md:PeopleLocal><md:PeopleLocal><md:Job><md:JobFunction>Producer</md:JobFunction><md:JobDisplay>Producer</md:JobDisplay><md:BillingBlockOrder>12</md:BillingBlockOrder></md:Job><md:Name><md:DisplayName>G. Mac Brown</md:DisplayName><md:SortName>Brown, G. Mac</md:SortName><md:FirstGivenName>G. Mac</md:FirstGivenName><md:FamilyName>Brown</md:FamilyName></md:Name></md:PeopleLocal><md:PeopleLocal><md:Job><md:JobFunction>Actor</md:JobFunction><md:BillingBlockOrder>7</md:BillingBlockOrder><md:Character>Sheriff Dollard</md:Character></md:Job><md:Name><md:DisplayName>Christopher Penn</md:DisplayName><md:SortName>Penn, Christopher</md:SortName><md:FirstGivenName>Christopher</md:FirstGivenName><md:FamilyName>Penn</md:FamilyName></md:Name></md:PeopleLocal><md:PeopleLocal><md:Job><md:JobFunction>Actor</md:JobFunction><md:BillingBlockOrder>4</md:BillingBlockOrder><md:Character>Carol Ann</md:Character></md:Job><md:Name><md:DisplayName>Stockard Channing</md:DisplayName><md:SortName>Channing, Stockard</md:SortName><md:FirstGivenName>Stockard</md:FirstGivenName><md:FamilyName>Channing</md:FamilyName></md:Name></md:PeopleLocal><md:PeopleLocal><md:Job><md:JobFunction>Actor</md:JobFunction><md:BillingBlockOrder>9</md:BillingBlockOrder><md:Character>Tommy</md:Character></md:Job><md:Name><md:DisplayName>Michael Vartan</md:DisplayName><md:SortName>Vartan, Michael</md:SortName><md:FirstGivenName>Michael</md:FirstGivenName><md:FamilyName>Vartan</md:FamilyName></md:Name></md:PeopleLocal><md:PeopleLocal><md:Job><md:JobFunction>Actor</md:JobFunction><md:BillingBlockOrder>3</md:BillingBlockOrder><md:Character>Chi Chi</md:Character></md:Job><md:Name><md:DisplayName>John Leguizamo</md:DisplayName><md:SortName>Leguizamo, John</md:SortName><md:FirstGivenName>John</md:FirstGivenName><md:FamilyName>Leguizamo</md:FamilyName></md:Name></md:PeopleLocal><md:PeopleLocal><md:Job><md:JobFunction>Actor</md:JobFunction><md:BillingBlockOrder>1</md:BillingBlockOrder><md:Character>Vida</md:Character></md:Job><md:Name><md:DisplayName>Patrick Swayze</md:DisplayName><md:SortName>Swayze, Patrick</md:SortName><md:FirstGivenName>Patrick</md:FirstGivenName><md:FamilyName>Swayze</md:FamilyName></md:Name></md:PeopleLocal><md:PeopleLocal><md:Job><md:JobFunction>Screenplay</md:JobFunction><md:JobDisplay>Screenplay</md:JobDisplay><md:BillingBlockOrder>13</md:BillingBlockOrder></md:Job><md:Name><md:DisplayName>Douglas Carter Beane</md:DisplayName><md:SortName>Beane, Douglas Carter</md:SortName><md:FirstGivenName>Douglas Carter</md:FirstGivenName><md:FamilyName>Beane</md:FamilyName></md:Name></md:PeopleLocal><md:PeopleLocal><md:Job><md:JobFunction>Actor</md:JobFunction><md:BillingBlockOrder>8</md:BillingBlockOrder><md:Character>Bobby Ray</md:Character></md:Job><md:Name><md:DisplayName>Jason London</md:DisplayName><md:SortName>London, Jason</md:SortName><md:FirstGivenName>Jason</md:FirstGivenName><md:FamilyName>London</md:FamilyName></md:Name></md:PeopleLocal><md:PeopleLocal><md:Job><md:JobFunction>Actor</md:JobFunction><md:BillingBlockOrder>6</md:BillingBlockOrder><md:Character>Virgil</md:Character></md:Job><md:Name><md:DisplayName>Arliss Howard</md:DisplayName><md:SortName>Howard, Arliss</md:SortName><md:FirstGivenName>Arliss</md:FirstGivenName><md:FamilyName>Howard</md:FamilyName></md:Name></md:PeopleLocal><md:PeopleLocal><md:Job><md:JobFunction>Director</md:JobFunction><md:JobDisplay>Director</md:JobDisplay><md:BillingBlockOrder>11</md:BillingBlockOrder></md:Job><md:Name><md:DisplayName>Beeban Kidron</md:DisplayName><md:SortName>Kidron, Beeban</md:SortName><md:FirstGivenName>Beeban</md:FirstGivenName><md:FamilyName>Kidron</md:FamilyName></md:Name></md:PeopleLocal><md:PeopleLocal><md:Job><md:JobFunction>Actor</md:JobFunction><md:BillingBlockOrder>5</md:BillingBlockOrder><md:Character>Beatrice</md:Character></md:Job><md:Name><md:DisplayName>Blythe Danner</md:DisplayName><md:SortName>Danner, Blythe</md:SortName><md:FirstGivenName>Blythe</md:FirstGivenName><md:FamilyName>Danner</md:FamilyName></md:Name></md:PeopleLocal></md:LocalizedInfo><md:RunLength>PT1H49M0.000S</md:RunLength><md:ReleaseYear>1995</md:ReleaseYear><md:ReleaseDate>1995-09-08</md:ReleaseDate><md:WorkType>Movie</md:WorkType><md:PictureColorType>color</md:PictureColorType><md:PictureFormat>Widescreen</md:PictureFormat><md:AltIdentifier><md:Namespace>UniversalHiDef</md:Namespace><md:Identifier>urn:universal:vendorid:U2228</md:Identifier><md:Location>http://www.universalhidef.com</md:Location></md:AltIdentifier><md:RatingSet><md:Rating><md:Region><md:country>US</md:country></md:Region><md:System>MPAA</md:System><md:Value>PG-13</md:Value></md:Rating><md:Rating><md:Region><md:country>CA</md:country></md:Region><md:System>CHVRS</md:System><md:Value>PG</md:Value></md:Rating></md:RatingSet><md:People><md:Job><md:JobFunction>Screenplay</md:JobFunction><md:JobDisplay>Screenplay</md:JobDisplay><md:BillingBlockOrder>13</md:BillingBlockOrder></md:Job><md:Name><md:DisplayName>Douglas Carter Beane</md:DisplayName><md:SortName>Beane, Douglas Carter</md:SortName><md:FirstGivenName>Douglas Carter</md:FirstGivenName><md:FamilyName>Beane</md:FamilyName></md:Name></md:People><md:People><md:Job><md:JobFunction>Director</md:JobFunction><md:JobDisplay>Director</md:JobDisplay><md:BillingBlockOrder>11</md:BillingBlockOrder></md:Job><md:Name><md:DisplayName>Beeban Kidron</md:DisplayName><md:SortName>Kidron, Beeban</md:SortName><md:FirstGivenName>Beeban</md:FirstGivenName><md:FamilyName>Kidron</md:FamilyName></md:Name></md:People><md:People><md:Job><md:JobFunction>Actor</md:JobFunction><md:BillingBlockOrder>6</md:BillingBlockOrder><md:Character>Virgil</md:Character></md:Job><md:Name><md:DisplayName>Arliss Howard</md:DisplayName><md:SortName>Howard, Arliss</md:SortName><md:FirstGivenName>Arliss</md:FirstGivenName><md:FamilyName>Howard</md:FamilyName></md:Name></md:People><md:People><md:Job><md:JobFunction>Actor</md:JobFunction><md:BillingBlockOrder>4</md:BillingBlockOrder><md:Character>Carol Ann</md:Character></md:Job><md:Name><md:DisplayName>Stockard Channing</md:DisplayName><md:SortName>Channing, Stockard</md:SortName><md:FirstGivenName>Stockard</md:FirstGivenName><md:FamilyName>Channing</md:FamilyName></md:Name></md:People><md:People><md:Job><md:JobFunction>Actor</md:JobFunction><md:BillingBlockOrder>8</md:BillingBlockOrder><md:Character>Bobby Ray</md:Character></md:Job><md:Name><md:DisplayName>Jason London</md:DisplayName><md:SortName>London, Jason</md:SortName><md:FirstGivenName>Jason</md:FirstGivenName><md:FamilyName>London</md:FamilyName></md:Name></md:People><md:People><md:Job><md:JobFunction>Actor</md:JobFunction><md:BillingBlockOrder>7</md:BillingBlockOrder><md:Character>Sheriff Dollard</md:Character></md:Job><md:Name><md:DisplayName>Christopher Penn</md:DisplayName><md:SortName>Penn, Christopher</md:SortName><md:FirstGivenName>Christopher</md:FirstGivenName><md:FamilyName>Penn</md:FamilyName></md:Name></md:People><md:People><md:Job><md:JobFunction>Actor</md:JobFunction><md:BillingBlockOrder>2</md:BillingBlockOrder><md:Character>Noxeema</md:Character></md:Job><md:Name><md:DisplayName>Wesley Snipes</md:DisplayName><md:SortName>Snipes, Wesley</md:SortName><md:FirstGivenName>Wesley</md:FirstGivenName><md:FamilyName>Snipes</md:FamilyName></md:Name></md:People><md:People><md:Job><md:JobFunction>Actor</md:JobFunction><md:BillingBlockOrder>3</md:BillingBlockOrder><md:Character>Chi Chi</md:Character></md:Job><md:Name><md:DisplayName>John Leguizamo</md:DisplayName><md:SortName>Leguizamo, John</md:SortName><md:FirstGivenName>John</md:FirstGivenName><md:FamilyName>Leguizamo</md:FamilyName></md:Name></md:People><md:People><md:Job><md:JobFunction>Actor</md:JobFunction><md:BillingBlockOrder>1</md:BillingBlockOrder><md:Character>Vida</md:Character></md:Job><md:Name><md:DisplayName>Patrick Swayze</md:DisplayName><md:SortName>Swayze, Patrick</md:SortName><md:FirstGivenName>Patrick</md:FirstGivenName><md:FamilyName>Swayze</md:FamilyName></md:Name></md:People><md:People><md:Job><md:JobFunction>Producer</md:JobFunction><md:JobDisplay>Producer</md:JobDisplay><md:BillingBlockOrder>12</md:BillingBlockOrder></md:Job><md:Name><md:DisplayName>G. Mac Brown</md:DisplayName><md:SortName>Brown, G. Mac</md:SortName><md:FirstGivenName>G. Mac</md:FirstGivenName><md:FamilyName>Brown</md:FamilyName></md:Name></md:People><md:People><md:Job><md:JobFunction>Actor</md:JobFunction><md:BillingBlockOrder>5</md:BillingBlockOrder><md:Character>Beatrice</md:Character></md:Job><md:Name><md:DisplayName>Blythe Danner</md:DisplayName><md:SortName>Danner, Blythe</md:SortName><md:FirstGivenName>Blythe</md:FirstGivenName><md:FamilyName>Danner</md:FamilyName></md:Name></md:People><md:People><md:Job><md:JobFunction>Actor</md:JobFunction><md:BillingBlockOrder>10</md:BillingBlockOrder><md:Character>Rachel Tensions</md:Character></md:Job><md:Name><md:DisplayName>RuPaul Charles</md:DisplayName><md:SortName>Charles, RuPaul</md:SortName><md:FirstGivenName>RuPaul</md:FirstGivenName><md:FamilyName>Charles</md:FamilyName></md:Name></md:People><md:People><md:Job><md:JobFunction>Actor</md:JobFunction><md:BillingBlockOrder>9</md:BillingBlockOrder><md:Character>Tommy</md:Character></md:Job><md:Name><md:DisplayName>Michael Vartan</md:DisplayName><md:SortName>Vartan, Michael</md:SortName><md:FirstGivenName>Michael</md:FirstGivenName><md:FamilyName>Vartan</md:FamilyName></md:Name></md:People><md:CountryOfOrigin><md:country>US</md:country></md:CountryOfOrigin></BasicData><ResourceStatus><Current CreatedBy="urn:dece:org:org:dece:ushe:contentprovider" CreationDate="2014-10-02T03:12:09.700Z" ModificationDate="2014-10-02T03:12:09.700Z" ModifiedBy="urn:dece:org:org:dece:ushe:contentprovider"><Value>urn:dece:type:status:active</Value></Current></ResourceStatus></BasicAsset>