<?xml version="1.0" encoding="UTF-8"?>
<BasicAsset xmlns:md="http://www.movielabs.com/schema/md/v2.3/md" xmlns:ns3="http://www.w3.org/2000/09/xmldsig#" xmlns="http://www.decellc.org/schema/2015/03/coordinator"><BasicData ContentID="urn:dece:cid:eidr-s:B6F2-8C73-F8FA-CF24-A929-L"><md:UpdateNum>22757253</md:UpdateNum><md:LocalizedInfo default="true" language="en"><md:TitleDisplay19>Frankie Go Boom</md:TitleDisplay19><md:TitleDisplay60>Frankie Go Boom</md:TitleDisplay60><md:TitleSort>Frankie Go Boom</md:TitleSort><md:ArtReference resolution="112x160">https://g.prod.uvvu.com/artwork/d9dd968f0123524ce0405b0a09340fbf</md:ArtReference><md:ArtReference resolution="117x176">https://g.prod.uvvu.com/artwork/d9dd968f0122524ce0405b0a09340fbf</md:ArtReference><md:ArtReference resolution="192x288">https://g.prod.uvvu.com/artwork/d9dd968f0124524ce0405b0a09340fbf</md:ArtReference><md:ArtReference resolution="224x320">https://g.prod.uvvu.com/artwork/d9dd968f0120524ce0405b0a09340fbf</md:ArtReference><md:ArtReference resolution="800x1200">https://g.prod.uvvu.com/artwork/d9dd968f0121524ce0405b0a09340fbf</md:ArtReference><md:ArtReference resolution="840x1200">https://g.prod.uvvu.com/artwork/d9dd968f011f524ce0405b0a09340fbf</md:ArtReference><md:ArtReference resolution="96x144">https://g.prod.uvvu.com/artwork/d9dd968f0125524ce0405b0a09340fbf</md:ArtReference><md:Summary190>Charlie Hunnam, Chris O’Dowd, Lizzy Caplan, Ron Perlman and Chris Noth star in this outrageous comedy about brotherly rivalry, amateur porn and the dangers of online fame.</md:Summary190><md:Summary400>Charlie Hunnam, Chris O’Dowd, Lizzy Caplan, Ron Perlman and Chris Noth star in this outrageous comedy about brotherly rivalry, amateur porn and the dangers of online fame.</md:Summary400><md:Summary4000>An insane comedy about two brothers, a girl with a broken heart, a sex tape, an angel. And a pig... For his whole life Frank (Charlie Hunnam) has been tortured, embarrassed and humiliated on film by his horrible brother, Bruce (Chris O’Dowd). When Bruce makes and uploads a video of a disastrous one-night stand of Frank’s, the sex tape immediately becomes a viral hit and things really hit the fan. Will Jack (Chris Noth), Bruce’s violent drug-fiend rehab buddy, find out it’s his daughter (Lizzy Caplan) in the video? Can Phyllis (Ron Perlman), Bruce’s transsexual computer hacker prison buddy, get them out of trouble? Frankie Go Boom is an outrageous comedy about brotherly hate, amateur porn and the dangers of online fame.</md:Summary4000><md:Genre>Comedy</md:Genre><md:OriginalTitle>Frankie Go Boom</md:OriginalTitle><md:CopyrightLine>© 2011 Universal Studios. All Rights Reserved.</md:CopyrightLine><md:PeopleLocal><md:Job><md:JobFunction>Actor</md:JobFunction><md:BillingBlockOrder>5</md:BillingBlockOrder><md:Character>Dad (Chris)</md:Character></md:Job><md:Name><md:DisplayName>Sam Anderson</md:DisplayName><md:SortName>Anderson, Sam</md:SortName><md:FirstGivenName>Sam</md:FirstGivenName><md:FamilyName>Anderson</md:FamilyName></md:Name></md:PeopleLocal><md:PeopleLocal><md:Job><md:JobFunction>Actor</md:JobFunction><md:BillingBlockOrder>4</md:BillingBlockOrder><md:Character>Mom (Karen)</md:Character></md:Job><md:Name><md:DisplayName>Nora Dunn</md:DisplayName><md:SortName>Dunn, Nora</md:SortName><md:FirstGivenName>Nora</md:FirstGivenName><md:FamilyName>Dunn</md:FamilyName></md:Name></md:PeopleLocal><md:PeopleLocal><md:Job><md:JobFunction>Producer</md:JobFunction><md:JobDisplay>Producer</md:JobDisplay><md:BillingBlockOrder>4</md:BillingBlockOrder></md:Job><md:Name><md:DisplayName>Katayoun A. Marciano</md:DisplayName><md:SortName>Marciano, Katayoun A.</md:SortName><md:FirstGivenName>Katayoun A.</md:FirstGivenName><md:FamilyName>Marciano</md:FamilyName></md:Name></md:PeopleLocal><md:PeopleLocal><md:Job><md:JobFunction>Screenplay</md:JobFunction><md:JobDisplay>Screenplay</md:JobDisplay><md:BillingBlockOrder>5</md:BillingBlockOrder></md:Job><md:Name><md:DisplayName>Jordan Roberts</md:DisplayName><md:SortName>Roberts, Jordan</md:SortName><md:FirstGivenName>Jordan</md:FirstGivenName><md:FamilyName>Roberts</md:FamilyName></md:Name></md:PeopleLocal><md:PeopleLocal><md:Job><md:JobFunction>Producer</md:JobFunction><md:JobDisplay>Producer</md:JobDisplay><md:BillingBlockOrder>3</md:BillingBlockOrder></md:Job><md:Name><md:DisplayName>Pavlina Hatoupis</md:DisplayName><md:SortName>Hatoupis, Pavlina</md:SortName><md:FirstGivenName>Pavlina</md:FirstGivenName><md:FamilyName>Hatoupis</md:FamilyName></md:Name></md:PeopleLocal><md:PeopleLocal><md:Job><md:JobFunction>Actor</md:JobFunction><md:BillingBlockOrder>2</md:BillingBlockOrder><md:Character>Bruce</md:Character></md:Job><md:Name><md:DisplayName>Chris O'Dowd</md:DisplayName><md:SortName>O'Dowd, Chris</md:SortName><md:FirstGivenName>Chris</md:FirstGivenName><md:FamilyName>O'Dowd</md:FamilyName></md:Name></md:PeopleLocal><md:PeopleLocal><md:Job><md:JobFunction>Director</md:JobFunction><md:JobDisplay>Director</md:JobDisplay><md:BillingBlockOrder>1</md:BillingBlockOrder></md:Job><md:Name><md:DisplayName>Jordan Roberts</md:DisplayName><md:SortName>Roberts, Jordan</md:SortName><md:FirstGivenName>Jordan</md:FirstGivenName><md:FamilyName>Roberts</md:FamilyName></md:Name></md:PeopleLocal><md:PeopleLocal><md:Job><md:JobFunction>Actor</md:JobFunction><md:BillingBlockOrder>3</md:BillingBlockOrder><md:Character>Lassie</md:Character></md:Job><md:Name><md:DisplayName>Lizzy Caplan</md:DisplayName><md:SortName>Caplan, Lizzy</md:SortName><md:FirstGivenName>Lizzy</md:FirstGivenName><md:FamilyName>Caplan</md:FamilyName></md:Name></md:PeopleLocal><md:PeopleLocal><md:Job><md:JobFunction>Producer</md:JobFunction><md:JobDisplay>Producer</md:JobDisplay><md:BillingBlockOrder>2</md:BillingBlockOrder></md:Job><md:Name><md:DisplayName>Marcel Langenegger</md:DisplayName><md:SortName>Langenegger, Marcel</md:SortName><md:FirstGivenName>Marcel</md:FirstGivenName><md:FamilyName>Langenegger</md:FamilyName></md:Name></md:PeopleLocal><md:PeopleLocal><md:Job><md:JobFunction>Actor</md:JobFunction><md:BillingBlockOrder>1</md:BillingBlockOrder><md:Character>Frankie</md:Character></md:Job><md:Name><md:DisplayName>Charlie Hunnam</md:DisplayName><md:SortName>Hunnam, Charlie</md:SortName><md:FirstGivenName>Charlie</md:FirstGivenName><md:FamilyName>Hunnam</md:FamilyName></md:Name></md:PeopleLocal><md:PeopleLocal><md:Job><md:JobFunction>Actor</md:JobFunction><md:BillingBlockOrder>7</md:BillingBlockOrder><md:Character>Jack</md:Character></md:Job><md:Name><md:DisplayName>Chris Noth</md:DisplayName><md:SortName>Noth, Chris</md:SortName><md:FirstGivenName>Chris</md:FirstGivenName><md:FamilyName>Noth</md:FamilyName></md:Name></md:PeopleLocal><md:PeopleLocal><md:Job><md:JobFunction>Actor</md:JobFunction><md:BillingBlockOrder>6</md:BillingBlockOrder><md:Character>Phyllis</md:Character></md:Job><md:Name><md:DisplayName>Ron Perlman</md:DisplayName><md:SortName>Perlman, Ron</md:SortName><md:FirstGivenName>Ron</md:FirstGivenName><md:FamilyName>Perlman</md:FamilyName></md:Name></md:PeopleLocal></md:LocalizedInfo><md:RunLength>PT1H29M0.000S</md:RunLength><md:ReleaseYear>2012</md:ReleaseYear><md:ReleaseDate>2012-10-12</md:ReleaseDate><md:WorkType>Movie</md:WorkType><md:PictureColorType>color</md:PictureColorType><md:PictureFormat>Widescreen</md:PictureFormat><md:AltIdentifier><md:Namespace>UniversalHiDef</md:Namespace><md:Identifier>urn:universal:vendorid:08E78</md:Identifier><md:Location>http://www.universalhidef.com</md:Location></md:AltIdentifier><md:RatingSet><md:Rating><md:Region><md:country>CA</md:country></md:Region><md:System>CHVRS</md:System><md:Value>14A</md:Value></md:Rating></md:RatingSet><md:People><md:Job><md:JobFunction>Screenplay</md:JobFunction><md:JobDisplay>Screenplay</md:JobDisplay><md:BillingBlockOrder>5</md:BillingBlockOrder></md:Job><md:Name><md:DisplayName>Jordan Roberts</md:DisplayName><md:SortName>Roberts, Jordan</md:SortName><md:FirstGivenName>Jordan</md:FirstGivenName><md:FamilyName>Roberts</md:FamilyName></md:Name></md:People><md:People><md:Job><md:JobFunction>Actor</md:JobFunction><md:BillingBlockOrder>2</md:BillingBlockOrder><md:Character>Bruce</md:Character></md:Job><md:Name><md:DisplayName>Chris O'Dowd</md:DisplayName><md:SortName>O'Dowd, Chris</md:SortName><md:FirstGivenName>Chris</md:FirstGivenName><md:FamilyName>O'Dowd</md:FamilyName></md:Name></md:People><md:People><md:Job><md:JobFunction>Actor</md:JobFunction><md:BillingBlockOrder>3</md:BillingBlockOrder><md:Character>Lassie</md:Character></md:Job><md:Name><md:DisplayName>Lizzy Caplan</md:DisplayName><md:SortName>Caplan, Lizzy</md:SortName><md:FirstGivenName>Lizzy</md:FirstGivenName><md:FamilyName>Caplan</md:FamilyName></md:Name></md:People><md:People><md:Job><md:JobFunction>Producer</md:JobFunction><md:JobDisplay>Producer</md:JobDisplay><md:BillingBlockOrder>3</md:BillingBlockOrder></md:Job><md:Name><md:DisplayName>Pavlina Hatoupis</md:DisplayName><md:SortName>Hatoupis, Pavlina</md:SortName><md:FirstGivenName>Pavlina</md:FirstGivenName><md:FamilyName>Hatoupis</md:FamilyName></md:Name></md:People><md:People><md:Job><md:JobFunction>Actor</md:JobFunction><md:BillingBlockOrder>4</md:BillingBlockOrder><md:Character>Mom (Karen)</md:Character></md:Job><md:Name><md:DisplayName>Nora Dunn</md:DisplayName><md:SortName>Dunn, Nora</md:SortName><md:FirstGivenName>Nora</md:FirstGivenName><md:FamilyName>Dunn</md:FamilyName></md:Name></md:People><md:People><md:Job><md:JobFunction>Producer</md:JobFunction><md:JobDisplay>Producer</md:JobDisplay><md:BillingBlockOrder>4</md:BillingBlockOrder></md:Job><md:Name><md:DisplayName>Katayoun A. Marciano</md:DisplayName><md:SortName>Marciano, Katayoun A.</md:SortName><md:FirstGivenName>Katayoun A.</md:FirstGivenName><md:FamilyName>Marciano</md:FamilyName></md:Name></md:People><md:People><md:Job><md:JobFunction>Actor</md:JobFunction><md:BillingBlockOrder>6</md:BillingBlockOrder><md:Character>Phyllis</md:Character></md:Job><md:Name><md:DisplayName>Ron Perlman</md:DisplayName><md:SortName>Perlman, Ron</md:SortName><md:FirstGivenName>Ron</md:FirstGivenName><md:FamilyName>Perlman</md:FamilyName></md:Name></md:People><md:People><md:Job><md:JobFunction>Actor</md:JobFunction><md:BillingBlockOrder>5</md:BillingBlockOrder><md:Character>Dad (Chris)</md:Character></md:Job><md:Name><md:DisplayName>Sam Anderson</md:DisplayName><md:SortName>Anderson, Sam</md:SortName><md:FirstGivenName>Sam</md:FirstGivenName><md:FamilyName>Anderson</md:FamilyName></md:Name></md:People><md:People><md:Job><md:JobFunction>Director</md:JobFunction><md:JobDisplay>Director</md:JobDisplay><md:BillingBlockOrder>1</md:BillingBlockOrder></md:Job><md:Name><md:DisplayName>Jordan Roberts</md:DisplayName><md:SortName>Roberts, Jordan</md:SortName><md:FirstGivenName>Jordan</md:FirstGivenName><md:FamilyName>Roberts</md:FamilyName></md:Name></md:People><md:People><md:Job><md:JobFunction>Producer</md:JobFunction><md:JobDisplay>Producer</md:JobDisplay><md:BillingBlockOrder>2</md:BillingBlockOrder></md:Job><md:Name><md:DisplayName>Marcel Langenegger</md:DisplayName><md:SortName>Langenegger, Marcel</md:SortName><md:FirstGivenName>Marcel</md:FirstGivenName><md:FamilyName>Langenegger</md:FamilyName></md:Name></md:People><md:People><md:Job><md:JobFunction>Actor</md:JobFunction><md:BillingBlockOrder>1</md:BillingBlockOrder><md:Character>Frankie</md:Character></md:Job><md:Name><md:DisplayName>Charlie Hunnam</md:DisplayName><md:SortName>Hunnam, Charlie</md:SortName><md:FirstGivenName>Charlie</md:FirstGivenName><md:FamilyName>Hunnam</md:FamilyName></md:Name></md:People><md:People><md:Job><md:JobFunction>Actor</md:JobFunction><md:BillingBlockOrder>7</md:BillingBlockOrder><md:Character>Jack</md:Character></md:Job><md:Name><md:DisplayName>Chris Noth</md:DisplayName><md:SortName>Noth, Chris</md:SortName><md:FirstGivenName>Chris</md:FirstGivenName><md:FamilyName>Noth</md:FamilyName></md:Name></md:People><md:CountryOfOrigin><md:country>US</md:country></md:CountryOfOrigin></BasicData><ResourceStatus><Current CreatedBy="urn:dece:org:org:dece:ushe:contentprovider" CreationDate="2013-04-08T17:19:26.348Z"><Value>urn:dece:type:status:active</Value></Current></ResourceStatus></BasicAsset>